onLoadData({
  "type": "FeatureCollection",
  "features": [{
      "type": "Feature",
      "geometry": {
        "type": "Point",
        "coordinates": [73.481, 18.729, 709]
      },
      "properties": {
        "name": "Bhaja",
        "Group": "Indrayani valley",
        "startYear": "third century BCE",
        "endYear": "200",
        "start": "-100",
        "end": "200",
        "when": {
          "timespans": [{
            "start": {
              "in": "-0100"
            },
            "end": {
              "in": "0200"
            }
          }],
          "periods": [{
              "name": "Early Historic",
              "@id": "periodo:p08m57hd85k"
            }
          ],
          "label": "",
          "duration": "P1000Y"
        },
      }
    },
    {
      "type": "Feature",
      "geometry": {
        "type": "Point",
        "coordinates": [73.884, 19.186, 782]
      },
      "properties": {
        "name": "Junnar Ambika",
        "Group": "Junnar",
        "startYear": "-150",
        "endYear": "400",
        "start": "-200",
        "end": "400"
      }
    },
    {
      "type": "Feature",
      "geometry": {
        "type": "Point",
        "coordinates": [72.905, 19.208, 140]
      },
      "properties": {
        "name": "Kanheri",
        "Group": "Kanheri environs",
        "startYear": "first century BCE to first century CE",
        "endYear": "late first millennium",
        "start": "100",
        "end": "900"
      }
    },
    {
      "type": "Feature",
      "geometry": {
        "type": "Point",
        "coordinates": [73.748, 19.941, 765]
      },
      "properties": {
        "name": "Nasik Pandu Lena",
        "Group": "Nasik",
        "startYear": "200",
        "endYear": "-200",
        "start": "050",
        "end": "200"
      }
    }
  ]
})
